LICENSE
MANIFEST.in
README.md
package.json
setup.py
dash_ant_design_components.egg-info/PKG-INFO
dash_ant_design_components.egg-info/SOURCES.txt
dash_ant_design_components.egg-info/dependency_links.txt
dash_ant_design_components.egg-info/top_level.txt
dash_antd_components/Button.py
dash_antd_components/ButtonGroup.py
dash_antd_components/Divider.py
dash_antd_components/GridCol.py
dash_antd_components/GridRow.py
dash_antd_components/Icon.py
dash_antd_components/Input.py
dash_antd_components/Layout.py
dash_antd_components/LayoutContent.py
dash_antd_components/LayoutFooter.py
dash_antd_components/LayoutHeader.py
dash_antd_components/LayoutSider.py
dash_antd_components/Space.py
dash_antd_components/Tooltip.py
dash_antd_components/Typography.py
dash_antd_components/TypographyLink.py
dash_antd_components/TypographyParagraph.py
dash_antd_components/TypographyText.py
dash_antd_components/TypographyTitle.py
dash_antd_components/__init__.py
dash_antd_components/_imports_.py
dash_antd_components/dash_antd_components.min.js
dash_antd_components/dash_antd_components.min.js.map
dash_antd_components/metadata.json
dash_antd_components/package-info.json