Metadata-Version: 1.1
Name: dash-ant-design-components
Version: 0.0.1
Summary: AntDesign components for Plotly Dash
Home-page: UNKNOWN
Author: Theo Li <bbtfrr@gmail.com>
Author-email: UNKNOWN
License: MIT
Platform: UNKNOWN
Classifier: Framework :: Dash
